{
    "applicationSpecification": {
        "applicationName": "Default Application",
        "versionMajor": 1,
        "versionMinor": 0,
        "versionPatch": 0,
        "versionVariant": 0
    },
    "windowProperties": {
        "windowTitle": "TurnipEngine v1.0",
        "dimensions": {
            "x": 800,
            "y": 600
        },
        "position": {
            "x": -1,
            "y": -1
        },
        "minSize": {
            "x": 300,
            "y": 300
        },
        "maxSize": {
            "x": 10000,
            "y": 10000
        }
    },
    "graphicsSpecifications": {
        "api": "OPENGL",
        "versionMajor": 4,
        "versionMinor": 3,
        "versionPatch": 0,
        "versionVariant": 0
    },
    "vulkanArguments": {
        "layers": [],
        "extensions": [],
        "enablePresentation": true,
        "addValidationLayer": false,
        "addDebugExtensions": false,
        "useDebugMessenger": false
    }
}
